pypfm/__init__.py
pypfm/pypfm.py
pypfm-1.4.4.dist-info/LICENSE
pypfm-1.4.4.dist-info/METADATA
pypfm-1.4.4.dist-info/WHEEL
pypfm-1.4.4.dist-info/top_level.txt
pypfm-1.4.4.dist-info/RECORD
