Metadata-Version: 2.1
Name: pypfm
Version: 1.4.4
Summary: Python pfm files reader
Home-page: https://github.com/Wats0ns/pypfm
Author: Wats0ns
Author-email: Wats0ns@github.com
License: MIT
Platform: UNKNOWN
Requires-Dist: pyzfp
Requires-Dist: numpy
